ezdxf/__init__.py
ezdxf/__main__.py
ezdxf/_options.py
ezdxf/appsettings.py
ezdxf/audit.py
ezdxf/bbox.py
ezdxf/blkrefs.py
ezdxf/colors.py
ezdxf/commands.py
ezdxf/comments.py
ezdxf/disassemble.py
ezdxf/document.py
ezdxf/dwginfo.py
ezdxf/dynblkhelper.py
ezdxf/edgeminer.py
ezdxf/edgesmith.py
ezdxf/entitydb.py
ezdxf/enums.py
ezdxf/explode.py
ezdxf/eztypes.py
ezdxf/filemanagement.py
ezdxf/gfxattribs.py
ezdxf/graphicsfactory.py
ezdxf/groupby.py
ezdxf/messenger.py
ezdxf/msgtypes.py
ezdxf/npshapes.py
ezdxf/protocols.py
ezdxf/proxygraphic.py
ezdxf/py.typed
ezdxf/query.py
ezdxf/queryparser.py
ezdxf/r12strict.py
ezdxf/recover.py
ezdxf/reorder.py
ezdxf/revcloud.py
ezdxf/select.py
ezdxf/transform.py
ezdxf/units.py
ezdxf/upright.py
ezdxf/urecord.py
ezdxf/version.py
ezdxf/xclip.py
ezdxf/xref.py
ezdxf/zoom.py
ezdxf/acc/__init__.py
ezdxf/acc/bezier3p.pyx
ezdxf/acc/bezier4p.pyx
ezdxf/acc/bspline.pyx
ezdxf/acc/constants.h
ezdxf/acc/construct.pyx
ezdxf/acc/linetypes.pyx
ezdxf/acc/mapbox_earcut.pyx
ezdxf/acc/matrix44.pxd
ezdxf/acc/matrix44.pyx
ezdxf/acc/np_support.pyx
ezdxf/acc/vector.pxd
ezdxf/acc/vector.pyx
ezdxf/acis/__init__.py
ezdxf/acis/abstract.py
ezdxf/acis/api.py
ezdxf/acis/cache.py
ezdxf/acis/const.py
ezdxf/acis/dbg.py
ezdxf/acis/dxf.py
ezdxf/acis/entities.py
ezdxf/acis/hdr.py
ezdxf/acis/mesh.py
ezdxf/acis/sab.py
ezdxf/acis/sat.py
ezdxf/acis/type_hints.py
ezdxf/addons/__init__.py
ezdxf/addons/acadctb.py
ezdxf/addons/binpacking.py
ezdxf/addons/dimlines.py
ezdxf/addons/dxf2code.py
ezdxf/addons/genetic_algorithm.py
ezdxf/addons/geo.py
ezdxf/addons/gerber_D6673.py
ezdxf/addons/importer.py
ezdxf/addons/iterdxf.py
ezdxf/addons/menger_sponge.py
ezdxf/addons/meshex.py
ezdxf/addons/mixins.py
ezdxf/addons/mtextsurrogate.py
ezdxf/addons/mtxpl.py
ezdxf/addons/odafc.py
ezdxf/addons/openscad.py
ezdxf/addons/pycsg.py
ezdxf/addons/r12export.py
ezdxf/addons/r12writer.py
ezdxf/addons/sierpinski_pyramid.py
ezdxf/addons/tablepainter.py
ezdxf/addons/text2path.py
ezdxf/addons/xplayer.py
ezdxf-1.4.3.dist-info/licenses/LICENSE
ezdxf-1.4.3.dist-info/METADATA
ezdxf-1.4.3.dist-info/WHEEL
ezdxf-1.4.3.dist-info/entry_points.txt
ezdxf-1.4.3.dist-info/top_level.txt
ezdxf-1.4.3.dist-info/RECORD
